{
"type": "FeatureCollection",
"crs": { "type": "name", "properties": { "name": "urn:ogc:def:crs:OGC:1.3:CRS84" } },
"features": [
{ "type": "Feature", "properties": { "Id": 0, "Descript": null, "Type": "WPT", "Comment": null, "Symbol": "Flag, Blue", "DateTimeS": "2020-06-15T12:49:01Z", "Elevation": 1686.383179, "IDENT": "001", "NAME": "Ramsey_WetDry" }, "geometry": { "type": "Point", "coordinates": [ -110.307005, 31.448242, 1686.383179 ] } },
{ "type": "Feature", "properties": { "Id": 0, "Descript": null, "Type": "WPT", "Comment": null, "Symbol": "Flag, Blue", "DateTimeS": "2020-06-15T14:01:12Z", "Elevation": 1888.711304, "IDENT": "002", "NAME": "Ramsey_WetDry" }, "geometry": { "type": "Point", "coordinates": [ -110.319228, 31.437318, 1888.711304 ] } },
{ "type": "Feature", "properties": { "Id": 0, "Descript": null, "Type": "WPT", "Comment": null, "Symbol": "Flag, Blue", "DateTimeS": "2020-06-15T14:28:07Z", "Elevation": 1934.888184, "IDENT": "003", "NAME": "Ramsey_WetDry" }, "geometry": { "type": "Point", "coordinates": [ -110.321374, 31.432735, 1934.888184 ] } },
{ "type": "Feature", "properties": { "Id": 0, "Descript": null, "Type": "WPT", "Comment": null, "Symbol": "Flag, Blue", "DateTimeS": "2020-06-15T14:33:40Z", "Elevation": 1938.881348, "IDENT": "004", "NAME": "Ramsey_WetDry" }, "geometry": { "type": "Point", "coordinates": [ -110.321699, 31.431572, 1938.881347999999889 ] } },
{ "type": "Feature", "properties": { "Id": 0, "Descript": null, "Type": "WPT", "Comment": null, "Symbol": "Flag, Blue", "DateTimeS": "2020-06-15T14:50:01Z", "Elevation": 2002.039795, "IDENT": "005", "NAME": "Ramsey_WetDry" }, "geometry": { "type": "Point", "coordinates": [ -110.322682, 31.428297, 2002.039795 ] } },
{ "type": "Feature", "properties": { "Id": 0, "Descript": null, "Type": "WPT", "Comment": null, "Symbol": "Flag, Blue", "DateTimeS": "2020-06-15T15:04:32Z", "Elevation": 2055.725098, "IDENT": "006", "NAME": "Ramsey_WetDry" }, "geometry": { "type": "Point", "coordinates": [ -110.325993, 31.425389, 2055.725097999999889 ] } },
{ "type": "Feature", "properties": { "Id": 0, "Descript": null, "Type": "WPT", "Comment": null, "Symbol": "Flag, Blue", "DateTimeS": "2020-06-15T15:40:13Z", "Elevation": 2159.298096, "IDENT": "007", "NAME": "Ramsey_WetDry" }, "geometry": { "type": "Point", "coordinates": [ -110.332113, 31.424133, 2159.298096 ] } },
{ "type": "Feature", "properties": { "Id": 0, "Descript": null, "Type": "WPT", "Comment": null, "Symbol": "Flag, Blue", "DateTimeS": "2020-06-15T15:47:05Z", "Elevation": 2180.349854, "IDENT": "008", "NAME": "Ramsey_WetDry" }, "geometry": { "type": "Point", "coordinates": [ -110.333699, 31.425132, 2180.349854 ] } },
{ "type": "Feature", "properties": { "Id": 0, "Descript": null, "Type": "WPT", "Comment": null, "Symbol": "Flag, Blue", "DateTimeS": "2020-06-15T16:29:57Z", "Elevation": 2237.596191, "IDENT": "009", "NAME": "Ramsey_WetDry" }, "geometry": { "type": "Point", "coordinates": [ -110.334776, 31.427125, 2237.596191 ] } },
{ "type": "Feature", "properties": { "Id": 0, "Descript": null, "Type": "WPT", "Comment": null, "Symbol": "Flag, Blue", "DateTimeS": "2020-06-15T16:32:23Z", "Elevation": 2252.626953, "IDENT": "010", "NAME": "Ramsey_WetDry" }, "geometry": { "type": "Point", "coordinates": [ -110.33491, 31.427169, 2252.626953 ] } },
{ "type": "Feature", "properties": { "Id": 0, "Descript": null, "Type": "WPT", "Comment": null, "Symbol": "Flag, Blue", "DateTimeS": "2020-06-15T16:35:48Z", "Elevation": 2257.77002, "IDENT": "011", "NAME": "Ramsey_WetDry" }, "geometry": { "type": "Point", "coordinates": [ -110.335444, 31.427531, 2257.77002 ] } },
{ "type": "Feature", "properties": { "Id": 0, "Descript": null, "Type": "WPT", "Comment": null, "Symbol": "Flag, Blue", "DateTimeS": "2020-06-15T16:37:52Z", "Elevation": 2262.452637, "IDENT": "012", "NAME": "Ramsey_WetDry" }, "geometry": { "type": "Point", "coordinates": [ -110.335656, 31.427532, 2262.452636999999868 ] } },
{ "type": "Feature", "properties": { "Id": 0, "Descript": null, "Type": "WPT", "Comment": null, "Symbol": "Flag, Blue", "DateTimeS": "2020-06-15T16:40:43Z", "Elevation": 2266.978271, "IDENT": "013", "NAME": "Ramsey_WetDry" }, "geometry": { "type": "Point", "coordinates": [ -110.33618, 31.42792, 2266.978271 ] } },
{ "type": "Feature", "properties": { "Id": 0, "Descript": null, "Type": "WPT", "Comment": null, "Symbol": "Flag, Blue", "DateTimeS": "2020-06-15T16:50:14Z", "Elevation": 2314.921387, "IDENT": "014", "NAME": "Ramsey_WetDry" }, "geometry": { "type": "Point", "coordinates": [ -110.338649, 31.429072, 2314.921386999999868 ] } }
]
}
